LICENSE
README.md
setup.cfg
setup.py
banksianz/__init__.py
banksianz/main.py
banksianz.egg-info/PKG-INFO
banksianz.egg-info/SOURCES.txt
banksianz.egg-info/dependency_links.txt
banksianz.egg-info/requires.txt
banksianz.egg-info/top_level.txt