Metadata-Version: 2.1
Name: banksianz
Version: 1.1
Summary: banksianz
Home-page: https://github.com/naistrai/banksianz
Download-URL: https://github.com/naistrai/banksianz/archive/v_01.tar.gz
Author: Naistrai
Author-email: rizkynaistrai@gmail.com
License: MIT
Project-URL: Documentation, https://github.com/naistrai/banksianz
Project-URL: Funding, https://donate.pypi.org
Project-URL: Say Thanks!, http://saythanks.io/to/example
Project-URL: Source, https://github.com/naistrai/banksianz/
Project-URL: Tracker, https://github.com/naistrai/banksianz/issues
Keywords: SOME,MEANINGFULL,KEYWORDS
Classifier: Development Status :: 3 - Alpha
Classifier: Intended Audience :: Developers
Classifier: Topic :: Software Development :: Build Tools
Classifier: License :: OSI Approved :: MIT License
Classifier: Programming Language :: Python :: 3
Classifier: Programming Language :: Python :: 3.4
Classifier: Programming Language :: Python :: 3.5
Classifier: Programming Language :: Python :: 3.6
License-File: LICENSE
Requires-Dist: validators
Requires-Dist: beautifulsoup4
Requires-Dist: discordautochat
Requires-Dist: discorudo
